[{"shape_id":"12292","shape_pt_lat":"36.166509","shape_pt_lon":"-86.780784","shape_pt_sequence":"1","shape_dist_traveled":"0.0"},{"shape_id":"12292","shape_pt_lat":"36.166368","shape_pt_lon":"-86.780706","shape_pt_sequence":"2","shape_dist_traveled":"0.0166"},{"shape_id":"12292","shape_pt_lat":"36.166281","shape_pt_lon":"-86.780643","shape_pt_sequence":"3","shape_dist_traveled":"0.0277"},{"shape_id":"12292","shape_pt_lat":"36.165902","shape_pt_lon":"-86.780392","shape_pt_sequence":"4","shape_dist_traveled":"0.0765"},{"shape_id":"12292","shape_pt_lat":"36.16579","shape_pt_lon":"-86.780324","shape_pt_sequence":"5","shape_dist_traveled":"0.0899"},{"shape_id":"12292","shape_pt_lat":"36.165498","shape_pt_lon":"-86.780125","shape_pt_sequence":"6","shape_dist_traveled":"0.127"},{"shape_id":"12292","shape_pt_lat":"36.165248","shape_pt_lon":"-86.779969","shape_pt_sequence":"7","shape_dist_traveled":"0.1583"},{"shape_id":"12292","shape_pt_lat":"36.165033","shape_pt_lon":"-86.779825","shape_pt_sequence":"8","shape_dist_traveled":"0.1856"},{"shape_id":"12292","shape_pt_lat":"36.164782","shape_pt_lon":"-86.779654","shape_pt_sequence":"9","shape_dist_traveled":"0.2174"},{"shape_id":"12292","shape_pt_lat":"36.164579","shape_pt_lon":"-86.779515","shape_pt_sequence":"10","shape_dist_traveled":"0.2438"},{"shape_id":"12292","shape_pt_lat":"36.164393","shape_pt_lon":"-86.779391","shape_pt_sequence":"11","shape_dist_traveled":"0.2675"},{"shape_id":"12292","shape_pt_lat":"36.164297","shape_pt_lon":"-86.779319","shape_pt_sequence":"12","shape_dist_traveled":"0.2792"},{"shape_id":"12292","shape_pt_lat":"36.163832","shape_pt_lon":"-86.779022","shape_pt_sequence":"13","shape_dist_traveled":"0.3387"},{"shape_id":"12292","shape_pt_lat":"36.16371","shape_pt_lon":"-86.778947","shape_pt_sequence":"14","shape_dist_traveled":"0.353"},{"shape_id":"12292","shape_pt_lat":"36.163346","shape_pt_lon":"-86.778708","shape_pt_sequence":"15","shape_dist_traveled":"0.3995"},{"shape_id":"12292","shape_pt_lat":"36.162853","shape_pt_lon":"-86.77839","shape_pt_sequence":"16","shape_dist_traveled":"0.4612"},{"shape_id":"12292","shape_pt_lat":"36.162547","shape_pt_lon":"-86.778173","shape_pt_sequence":"17","shape_dist_traveled":"0.5002"},{"shape_id":"12292","shape_pt_lat":"36.162402","shape_pt_lon":"-86.778084","shape_pt_sequence":"18","shape_dist_traveled":"0.519"},{"shape_id":"12292","shape_pt_lat":"36.162138","shape_pt_lon":"-86.777912","shape_pt_sequence":"19","shape_dist_traveled":"0.5521"},{"shape_id":"12292","shape_pt_lat":"36.161911","shape_pt_lon":"-86.777758","shape_pt_sequence":"20","shape_dist_traveled":"0.5812"},{"shape_id":"12292","shape_pt_lat":"36.161569","shape_pt_lon":"-86.777534","shape_pt_sequence":"21","shape_dist_traveled":"0.6241"},{"shape_id":"12292","shape_pt_lat":"36.161418","shape_pt_lon":"-86.777421","shape_pt_sequence":"22","shape_dist_traveled":"0.6438"},{"shape_id":"12292","shape_pt_lat":"36.161375","shape_pt_lon":"-86.777394","shape_pt_sequence":"23","shape_dist_traveled":"0.6497"},{"shape_id":"12292","shape_pt_lat":"36.161072","shape_pt_lon":"-86.777192","shape_pt_sequence":"24","shape_dist_traveled":"0.6881"},{"shape_id":"12292","shape_pt_lat":"36.160692","shape_pt_lon":"-86.776935","shape_pt_sequence":"25","shape_dist_traveled":"0.736"},{"shape_id":"12292","shape_pt_lat":"36.16032","shape_pt_lon":"-86.776697","shape_pt_sequence":"26","shape_dist_traveled":"0.783"},{"shape_id":"12292","shape_pt_lat":"36.159944","shape_pt_lon":"-86.776476","shape_pt_sequence":"27","shape_dist_traveled":"0.8295"},{"shape_id":"12292","shape_pt_lat":"36.159663","shape_pt_lon":"-86.77631","shape_pt_sequence":"28","shape_dist_traveled":"0.8635"},{"shape_id":"12292","shape_pt_lat":"36.15902","shape_pt_lon":"-86.775854","shape_pt_sequence":"29","shape_dist_traveled":"0.9464"},{"shape_id":"12292","shape_pt_lat":"36.158615","shape_pt_lon":"-86.775567","shape_pt_sequence":"30","shape_dist_traveled":"0.9992"},{"shape_id":"12292","shape_pt_lat":"36.158236","shape_pt_lon":"-86.775339","shape_pt_sequence":"31","shape_dist_traveled":"1.0457"},{"shape_id":"12292","shape_pt_lat":"36.157815","shape_pt_lon":"-86.775087","shape_pt_sequence":"32","shape_dist_traveled":"1.098"},{"shape_id":"12292","shape_pt_lat":"36.157427","shape_pt_lon":"-86.77482","shape_pt_sequence":"33","shape_dist_traveled":"1.1477"},{"shape_id":"12292","shape_pt_lat":"36.15721","shape_pt_lon":"-86.774684","shape_pt_sequence":"34","shape_dist_traveled":"1.1745"},{"shape_id":"12292","shape_pt_lat":"36.157035","shape_pt_lon":"-86.774576","shape_pt_sequence":"35","shape_dist_traveled":"1.1969"},{"shape_id":"12292","shape_pt_lat":"36.156995","shape_pt_lon":"-86.774545","shape_pt_sequence":"36","shape_dist_traveled":"1.2019"},{"shape_id":"12292","shape_pt_lat":"36.156534","shape_pt_lon":"-86.77427","shape_pt_sequence":"37","shape_dist_traveled":"1.2592"},{"shape_id":"12292","shape_pt_lat":"36.156113","shape_pt_lon":"-86.773997","shape_pt_sequence":"38","shape_dist_traveled":"1.3124"},{"shape_id":"12292","shape_pt_lat":"36.156054","shape_pt_lon":"-86.773961","shape_pt_sequence":"39","shape_dist_traveled":"1.32"},{"shape_id":"12292","shape_pt_lat":"36.155966","shape_pt_lon":"-86.773905","shape_pt_sequence":"40","shape_dist_traveled":"1.3303"},{"shape_id":"12292","shape_pt_lat":"36.15589","shape_pt_lon":"-86.773857","shape_pt_sequence":"41","shape_dist_traveled":"1.3402"},{"shape_id":"12292","shape_pt_lat":"36.155503","shape_pt_lon":"-86.773624","shape_pt_sequence":"42","shape_dist_traveled":"1.388"},{"shape_id":"12292","shape_pt_lat":"36.154962","shape_pt_lon":"-86.773272","shape_pt_sequence":"43","shape_dist_traveled":"1.4564"},{"shape_id":"12292","shape_pt_lat":"36.154745","shape_pt_lon":"-86.773128","shape_pt_sequence":"44","shape_dist_traveled":"1.4837"},{"shape_id":"12292","shape_pt_lat":"36.154699","shape_pt_lon":"-86.773098","shape_pt_sequence":"45","shape_dist_traveled":"1.4896"},{"shape_id":"12292","shape_pt_lat":"36.154208","shape_pt_lon":"-86.772777","shape_pt_sequence":"46","shape_dist_traveled":"1.5517"},{"shape_id":"12292","shape_pt_lat":"36.153842","shape_pt_lon":"-86.772539","shape_pt_sequence":"47","shape_dist_traveled":"1.5978"},{"shape_id":"12292","shape_pt_lat":"36.153284","shape_pt_lon":"-86.772182","shape_pt_sequence":"48","shape_dist_traveled":"1.6685"},{"shape_id":"12292","shape_pt_lat":"36.152335","shape_pt_lon":"-86.771576","shape_pt_sequence":"49","shape_dist_traveled":"1.7874"},{"shape_id":"12292","shape_pt_lat":"36.152063","shape_pt_lon":"-86.771401","shape_pt_sequence":"50","shape_dist_traveled":"1.821"},{"shape_id":"12292","shape_pt_lat":"36.151862","shape_pt_lon":"-86.771273","shape_pt_sequence":"51","shape_dist_traveled":"1.8469"},{"shape_id":"12292","shape_pt_lat":"36.151812","shape_pt_lon":"-86.77124","shape_pt_sequence":"52","shape_dist_traveled":"1.8536"},{"shape_id":"12292","shape_pt_lat":"36.151704","shape_pt_lon":"-86.77117","shape_pt_sequence":"53","shape_dist_traveled":"1.867"},{"shape_id":"12292","shape_pt_lat":"36.15111","shape_pt_lon":"-86.770739","shape_pt_sequence":"54","shape_dist_traveled":"1.9432"},{"shape_id":"12292","shape_pt_lat":"36.150956","shape_pt_lon":"-86.770636","shape_pt_sequence":"55","shape_dist_traveled":"1.9624"},{"shape_id":"12292","shape_pt_lat":"36.150775","shape_pt_lon":"-86.770514","shape_pt_sequence":"56","shape_dist_traveled":"1.9861"},{"shape_id":"12292","shape_pt_lat":"36.150656","shape_pt_lon":"-86.770442","shape_pt_sequence":"57","shape_dist_traveled":"2.0009"},{"shape_id":"12292","shape_pt_lat":"36.150501","shape_pt_lon":"-86.770346","shape_pt_sequence":"58","shape_dist_traveled":"2.0197"},{"shape_id":"12292","shape_pt_lat":"36.150231","shape_pt_lon":"-86.770185","shape_pt_sequence":"59","shape_dist_traveled":"2.0541"},{"shape_id":"12292","shape_pt_lat":"36.149676","shape_pt_lon":"-86.769819","shape_pt_sequence":"60","shape_dist_traveled":"2.1239"},{"shape_id":"12292","shape_pt_lat":"36.149427","shape_pt_lon":"-86.76965","shape_pt_sequence":"61","shape_dist_traveled":"2.1557"},{"shape_id":"12292","shape_pt_lat":"36.148876","shape_pt_lon":"-86.769286","shape_pt_sequence":"62","shape_dist_traveled":"2.225"},{"shape_id":"12292","shape_pt_lat":"36.14847","shape_pt_lon":"-86.769019","shape_pt_sequence":"63","shape_dist_traveled":"2.2769"},{"shape_id":"12292","shape_pt_lat":"36.14763","shape_pt_lon":"-86.768456","shape_pt_sequence":"64","shape_dist_traveled":"2.3834"},{"shape_id":"12292","shape_pt_lat":"36.147512","shape_pt_lon":"-86.768376","shape_pt_sequence":"65","shape_dist_traveled":"2.3981"},{"shape_id":"12292","shape_pt_lat":"36.146521","shape_pt_lon":"-86.767705","shape_pt_sequence":"66","shape_dist_traveled":"2.5243"},{"shape_id":"12292","shape_pt_lat":"36.145882","shape_pt_lon":"-86.767283","shape_pt_sequence":"67","shape_dist_traveled":"2.6057"},{"shape_id":"12292","shape_pt_lat":"36.145582","shape_pt_lon":"-86.767084","shape_pt_sequence":"68","shape_dist_traveled":"2.6428"},{"shape_id":"12292","shape_pt_lat":"36.144933","shape_pt_lon":"-86.766653","shape_pt_sequence":"69","shape_dist_traveled":"2.7256"},{"shape_id":"12292","shape_pt_lat":"36.144618","shape_pt_lon":"-86.766445","shape_pt_sequence":"70","shape_dist_traveled":"2.765"},{"shape_id":"12292","shape_pt_lat":"36.144191","shape_pt_lon":"-86.766167","shape_pt_sequence":"71","shape_dist_traveled":"2.8191"},{"shape_id":"12292","shape_pt_lat":"36.143645","shape_pt_lon":"-86.765811","shape_pt_sequence":"72","shape_dist_traveled":"2.888"},{"shape_id":"12292","shape_pt_lat":"36.142738","shape_pt_lon":"-86.765226","shape_pt_sequence":"73","shape_dist_traveled":"3.0025"},{"shape_id":"12292","shape_pt_lat":"36.142538","shape_pt_lon":"-86.765096","shape_pt_sequence":"74","shape_dist_traveled":"3.0275"},{"shape_id":"12292","shape_pt_lat":"36.142439","shape_pt_lon":"-86.765033","shape_pt_sequence":"75","shape_dist_traveled":"3.0396"},{"shape_id":"12292","shape_pt_lat":"36.14225","shape_pt_lon":"-86.764899","shape_pt_sequence":"76","shape_dist_traveled":"3.0638"},{"shape_id":"12292","shape_pt_lat":"36.142109","shape_pt_lon":"-86.764808","shape_pt_sequence":"77","shape_dist_traveled":"3.0817"},{"shape_id":"12292","shape_pt_lat":"36.141921","shape_pt_lon":"-86.764691","shape_pt_sequence":"78","shape_dist_traveled":"3.1054"},{"shape_id":"12292","shape_pt_lat":"36.141616","shape_pt_lon":"-86.764497","shape_pt_sequence":"79","shape_dist_traveled":"3.1434"},{"shape_id":"12292","shape_pt_lat":"36.141408","shape_pt_lon":"-86.764358","shape_pt_sequence":"80","shape_dist_traveled":"3.1702"},{"shape_id":"12292","shape_pt_lat":"36.141063","shape_pt_lon":"-86.76413","shape_pt_sequence":"81","shape_dist_traveled":"3.2136"},{"shape_id":"12292","shape_pt_lat":"36.140848","shape_pt_lon":"-86.763988","shape_pt_sequence":"82","shape_dist_traveled":"3.2405"},{"shape_id":"12292","shape_pt_lat":"36.140474","shape_pt_lon":"-86.763729","shape_pt_sequence":"83","shape_dist_traveled":"3.2889"},{"shape_id":"12292","shape_pt_lat":"36.140146","shape_pt_lon":"-86.763481","shape_pt_sequence":"84","shape_dist_traveled":"3.3319"},{"shape_id":"12292","shape_pt_lat":"36.13977","shape_pt_lon":"-86.763197","shape_pt_sequence":"85","shape_dist_traveled":"3.3808"},{"shape_id":"12292","shape_pt_lat":"36.139445","shape_pt_lon":"-86.762957","shape_pt_sequence":"86","shape_dist_traveled":"3.4225"},{"shape_id":"12292","shape_pt_lat":"36.139395","shape_pt_lon":"-86.762921","shape_pt_sequence":"87","shape_dist_traveled":"3.4297"},{"shape_id":"12292","shape_pt_lat":"36.139083","shape_pt_lon":"-86.76268","shape_pt_sequence":"88","shape_dist_traveled":"3.4705"},{"shape_id":"12292","shape_pt_lat":"36.138749","shape_pt_lon":"-86.762418","shape_pt_sequence":"89","shape_dist_traveled":"3.514"},{"shape_id":"12292","shape_pt_lat":"36.138447","shape_pt_lon":"-86.762192","shape_pt_sequence":"90","shape_dist_traveled":"3.554"},{"shape_id":"12292","shape_pt_lat":"36.138267","shape_pt_lon":"-86.76206","shape_pt_sequence":"91","shape_dist_traveled":"3.5768"},{"shape_id":"12292","shape_pt_lat":"36.137942","shape_pt_lon":"-86.761817","shape_pt_sequence":"92","shape_dist_traveled":"3.6199"},{"shape_id":"12292","shape_pt_lat":"36.137673","shape_pt_lon":"-86.761622","shape_pt_sequence":"93","shape_dist_traveled":"3.6549"},{"shape_id":"12292","shape_pt_lat":"36.1375","shape_pt_lon":"-86.761496","shape_pt_sequence":"94","shape_dist_traveled":"3.6768"},{"shape_id":"12292","shape_pt_lat":"36.13735","shape_pt_lon":"-86.761388","shape_pt_sequence":"95","shape_dist_traveled":"3.6961"},{"shape_id":"12292","shape_pt_lat":"36.137043","shape_pt_lon":"-86.761167","shape_pt_sequence":"96","shape_dist_traveled":"3.7355"},{"shape_id":"12292","shape_pt_lat":"36.136919","shape_pt_lon":"-86.761076","shape_pt_sequence":"97","shape_dist_traveled":"3.7516"},{"shape_id":"12292","shape_pt_lat":"36.136773","shape_pt_lon":"-86.760966","shape_pt_sequence":"98","shape_dist_traveled":"3.7714"},{"shape_id":"12292","shape_pt_lat":"36.136557","shape_pt_lon":"-86.760808","shape_pt_sequence":"99","shape_dist_traveled":"3.7991"},{"shape_id":"12292","shape_pt_lat":"36.136387","shape_pt_lon":"-86.760685","shape_pt_sequence":"100","shape_dist_traveled":"3.8211"},{"shape_id":"12292","shape_pt_lat":"36.136304","shape_pt_lon":"-86.760613","shape_pt_sequence":"101","shape_dist_traveled":"3.8325"},{"shape_id":"12292","shape_pt_lat":"36.136092","shape_pt_lon":"-86.760456","shape_pt_sequence":"102","shape_dist_traveled":"3.8603"},{"shape_id":"12292","shape_pt_lat":"36.136017","shape_pt_lon":"-86.760403","shape_pt_sequence":"103","shape_dist_traveled":"3.8692"},{"shape_id":"12292","shape_pt_lat":"36.135645","shape_pt_lon":"-86.760142","shape_pt_sequence":"104","shape_dist_traveled":"3.9176"},{"shape_id":"12292","shape_pt_lat":"36.135599","shape_pt_lon":"-86.760021","shape_pt_sequence":"105","shape_dist_traveled":"3.9288"},{"shape_id":"12292","shape_pt_lat":"36.135437","shape_pt_lon":"-86.759906","shape_pt_sequence":"106","shape_dist_traveled":"3.9499"},{"shape_id":"12292","shape_pt_lat":"36.135423","shape_pt_lon":"-86.759897","shape_pt_sequence":"107","shape_dist_traveled":"3.9519"},{"shape_id":"12292","shape_pt_lat":"36.135313","shape_pt_lon":"-86.759819","shape_pt_sequence":"108","shape_dist_traveled":"3.9658"},{"shape_id":"12292","shape_pt_lat":"36.1351","shape_pt_lon":"-86.759673","shape_pt_sequence":"109","shape_dist_traveled":"3.9931"},{"shape_id":"12292","shape_pt_lat":"36.134863","shape_pt_lon":"-86.75951","shape_pt_sequence":"110","shape_dist_traveled":"4.0239"},{"shape_id":"12292","shape_pt_lat":"36.134701","shape_pt_lon":"-86.759399","shape_pt_sequence":"111","shape_dist_traveled":"4.0445"},{"shape_id":"12292","shape_pt_lat":"36.134539","shape_pt_lon":"-86.759286","shape_pt_sequence":"112","shape_dist_traveled":"4.0651"},{"shape_id":"12292","shape_pt_lat":"36.134442","shape_pt_lon":"-86.759219","shape_pt_sequence":"113","shape_dist_traveled":"4.0777"},{"shape_id":"12292","shape_pt_lat":"36.134344","shape_pt_lon":"-86.759152","shape_pt_sequence":"114","shape_dist_traveled":"4.0902"},{"shape_id":"12292","shape_pt_lat":"36.134191","shape_pt_lon":"-86.759048","shape_pt_sequence":"115","shape_dist_traveled":"4.1094"},{"shape_id":"12292","shape_pt_lat":"36.134043","shape_pt_lon":"-86.758939","shape_pt_sequence":"116","shape_dist_traveled":"4.1283"},{"shape_id":"12292","shape_pt_lat":"36.133936","shape_pt_lon":"-86.758856","shape_pt_sequence":"117","shape_dist_traveled":"4.1422"},{"shape_id":"12292","shape_pt_lat":"36.133683","shape_pt_lon":"-86.758661","shape_pt_sequence":"118","shape_dist_traveled":"4.1763"},{"shape_id":"12292","shape_pt_lat":"36.133514","shape_pt_lon":"-86.758531","shape_pt_sequence":"119","shape_dist_traveled":"4.1983"},{"shape_id":"12292","shape_pt_lat":"36.133362","shape_pt_lon":"-86.758414","shape_pt_sequence":"120","shape_dist_traveled":"4.2185"},{"shape_id":"12292","shape_pt_lat":"36.133252","shape_pt_lon":"-86.758403","shape_pt_sequence":"121","shape_dist_traveled":"4.2306"},{"shape_id":"12292","shape_pt_lat":"36.133031","shape_pt_lon":"-86.758211","shape_pt_sequence":"122","shape_dist_traveled":"4.2608"},{"shape_id":"12292","shape_pt_lat":"36.132747","shape_pt_lon":"-86.757949","shape_pt_sequence":"123","shape_dist_traveled":"4.2994"},{"shape_id":"12292","shape_pt_lat":"36.132631","shape_pt_lon":"-86.757831","shape_pt_sequence":"124","shape_dist_traveled":"4.3164"},{"shape_id":"12292","shape_pt_lat":"36.132253","shape_pt_lon":"-86.757437","shape_pt_sequence":"125","shape_dist_traveled":"4.3719"},{"shape_id":"12292","shape_pt_lat":"36.131833","shape_pt_lon":"-86.756979","shape_pt_sequence":"126","shape_dist_traveled":"4.4342"},{"shape_id":"12292","shape_pt_lat":"36.131758","shape_pt_lon":"-86.756897","shape_pt_sequence":"127","shape_dist_traveled":"4.4449"},{"shape_id":"12292","shape_pt_lat":"36.131704","shape_pt_lon":"-86.756821","shape_pt_sequence":"128","shape_dist_traveled":"4.4541"},{"shape_id":"12292","shape_pt_lat":"36.131259","shape_pt_lon":"-86.756311","shape_pt_sequence":"129","shape_dist_traveled":"4.5214"},{"shape_id":"12292","shape_pt_lat":"36.131027","shape_pt_lon":"-86.756046","shape_pt_sequence":"130","shape_dist_traveled":"4.5567"},{"shape_id":"12292","shape_pt_lat":"36.130979","shape_pt_lon":"-86.755992","shape_pt_sequence":"131","shape_dist_traveled":"4.5638"},{"shape_id":"12292","shape_pt_lat":"36.130697","shape_pt_lon":"-86.755658","shape_pt_sequence":"132","shape_dist_traveled":"4.6077"},{"shape_id":"12292","shape_pt_lat":"36.130508","shape_pt_lon":"-86.755437","shape_pt_sequence":"133","shape_dist_traveled":"4.636"},{"shape_id":"12292","shape_pt_lat":"36.130474","shape_pt_lon":"-86.755309","shape_pt_sequence":"134","shape_dist_traveled":"4.6486"},{"shape_id":"12292","shape_pt_lat":"36.130292","shape_pt_lon":"-86.755119","shape_pt_sequence":"135","shape_dist_traveled":"4.6749"},{"shape_id":"12292","shape_pt_lat":"36.130172","shape_pt_lon":"-86.755011","shape_pt_sequence":"136","shape_dist_traveled":"4.6915"},{"shape_id":"12292","shape_pt_lat":"36.130103","shape_pt_lon":"-86.75495","shape_pt_sequence":"137","shape_dist_traveled":"4.7008"},{"shape_id":"12292","shape_pt_lat":"36.129949","shape_pt_lon":"-86.754818","shape_pt_sequence":"138","shape_dist_traveled":"4.7224"},{"shape_id":"12292","shape_pt_lat":"36.129763","shape_pt_lon":"-86.754678","shape_pt_sequence":"139","shape_dist_traveled":"4.7466"},{"shape_id":"12292","shape_pt_lat":"36.129606","shape_pt_lon":"-86.754588","shape_pt_sequence":"140","shape_dist_traveled":"4.7654"},{"shape_id":"12292","shape_pt_lat":"36.12949","shape_pt_lon":"-86.754522","shape_pt_sequence":"141","shape_dist_traveled":"4.7797"},{"shape_id":"12292","shape_pt_lat":"36.129329","shape_pt_lon":"-86.754431","shape_pt_sequence":"142","shape_dist_traveled":"4.7994"},{"shape_id":"12292","shape_pt_lat":"36.128346","shape_pt_lon":"-86.753904","shape_pt_sequence":"143","shape_dist_traveled":"4.919"},{"shape_id":"12292","shape_pt_lat":"36.128242","shape_pt_lon":"-86.75385","shape_pt_sequence":"144","shape_dist_traveled":"4.932"},{"shape_id":"12292","shape_pt_lat":"36.12796","shape_pt_lon":"-86.753702","shape_pt_sequence":"145","shape_dist_traveled":"4.9656"},{"shape_id":"12292","shape_pt_lat":"36.127357","shape_pt_lon":"-86.753387","shape_pt_sequence":"146","shape_dist_traveled":"5.0392"},{"shape_id":"12292","shape_pt_lat":"36.126872","shape_pt_lon":"-86.753126","shape_pt_sequence":"147","shape_dist_traveled":"5.0982"},{"shape_id":"12292","shape_pt_lat":"36.126386","shape_pt_lon":"-86.752864","shape_pt_sequence":"148","shape_dist_traveled":"5.1579"},{"shape_id":"12292","shape_pt_lat":"36.125865","shape_pt_lon":"-86.752586","shape_pt_sequence":"149","shape_dist_traveled":"5.221"},{"shape_id":"12292","shape_pt_lat":"36.125016","shape_pt_lon":"-86.75214","shape_pt_sequence":"150","shape_dist_traveled":"5.3241"},{"shape_id":"12292","shape_pt_lat":"36.124988","shape_pt_lon":"-86.752126","shape_pt_sequence":"151","shape_dist_traveled":"5.3273"},{"shape_id":"12292","shape_pt_lat":"36.124261","shape_pt_lon":"-86.751781","shape_pt_sequence":"152","shape_dist_traveled":"5.4149"},{"shape_id":"12292","shape_pt_lat":"36.124089","shape_pt_lon":"-86.751698","shape_pt_sequence":"153","shape_dist_traveled":"5.4352"},{"shape_id":"12292","shape_pt_lat":"36.123869","shape_pt_lon":"-86.751596","shape_pt_sequence":"154","shape_dist_traveled":"5.4617"},{"shape_id":"12292","shape_pt_lat":"36.123163","shape_pt_lon":"-86.751263","shape_pt_sequence":"155","shape_dist_traveled":"5.5462"},{"shape_id":"12292","shape_pt_lat":"36.123046","shape_pt_lon":"-86.75121","shape_pt_sequence":"156","shape_dist_traveled":"5.5602"},{"shape_id":"12292","shape_pt_lat":"36.122918","shape_pt_lon":"-86.751147","shape_pt_sequence":"157","shape_dist_traveled":"5.575"},{"shape_id":"12292","shape_pt_lat":"36.122838","shape_pt_lon":"-86.75111","shape_pt_sequence":"158","shape_dist_traveled":"5.5849"},{"shape_id":"12292","shape_pt_lat":"36.122736","shape_pt_lon":"-86.751065","shape_pt_sequence":"159","shape_dist_traveled":"5.5966"},{"shape_id":"12292","shape_pt_lat":"36.121844","shape_pt_lon":"-86.750646","shape_pt_sequence":"160","shape_dist_traveled":"5.7032"},{"shape_id":"12292","shape_pt_lat":"36.121545","shape_pt_lon":"-86.750502","shape_pt_sequence":"161","shape_dist_traveled":"5.7396"},{"shape_id":"12292","shape_pt_lat":"36.121384","shape_pt_lon":"-86.750422","shape_pt_sequence":"162","shape_dist_traveled":"5.7589"},{"shape_id":"12292","shape_pt_lat":"36.121087","shape_pt_lon":"-86.750271","shape_pt_sequence":"163","shape_dist_traveled":"5.7944"},{"shape_id":"12292","shape_pt_lat":"36.120609","shape_pt_lon":"-86.750028","shape_pt_sequence":"164","shape_dist_traveled":"5.8527"},{"shape_id":"12292","shape_pt_lat":"36.120549","shape_pt_lon":"-86.749997","shape_pt_sequence":"165","shape_dist_traveled":"5.8594"},{"shape_id":"12292","shape_pt_lat":"36.120408","shape_pt_lon":"-86.74993","shape_pt_sequence":"166","shape_dist_traveled":"5.8765"},{"shape_id":"12292","shape_pt_lat":"36.120069","shape_pt_lon":"-86.749769","shape_pt_sequence":"167","shape_dist_traveled":"5.917"},{"shape_id":"12292","shape_pt_lat":"36.119808","shape_pt_lon":"-86.749652","shape_pt_sequence":"168","shape_dist_traveled":"5.948"},{"shape_id":"12292","shape_pt_lat":"36.119141","shape_pt_lon":"-86.749323","shape_pt_sequence":"169","shape_dist_traveled":"6.0284"},{"shape_id":"12292","shape_pt_lat":"36.118947","shape_pt_lon":"-86.749226","shape_pt_sequence":"170","shape_dist_traveled":"6.0522"},{"shape_id":"12292","shape_pt_lat":"36.118854","shape_pt_lon":"-86.74918","shape_pt_sequence":"171","shape_dist_traveled":"6.063"},{"shape_id":"12292","shape_pt_lat":"36.11791","shape_pt_lon":"-86.74872","shape_pt_sequence":"172","shape_dist_traveled":"6.1766"},{"shape_id":"12292","shape_pt_lat":"36.117801","shape_pt_lon":"-86.748666","shape_pt_sequence":"173","shape_dist_traveled":"6.1896"},{"shape_id":"12292","shape_pt_lat":"36.11747","shape_pt_lon":"-86.748506","shape_pt_sequence":"174","shape_dist_traveled":"6.2292"},{"shape_id":"12292","shape_pt_lat":"36.116985","shape_pt_lon":"-86.74827","shape_pt_sequence":"175","shape_dist_traveled":"6.2871"},{"shape_id":"12292","shape_pt_lat":"36.116475","shape_pt_lon":"-86.748022","shape_pt_sequence":"176","shape_dist_traveled":"6.3482"},{"shape_id":"12292","shape_pt_lat":"36.11606","shape_pt_lon":"-86.74782","shape_pt_sequence":"177","shape_dist_traveled":"6.3986"},{"shape_id":"12292","shape_pt_lat":"36.115947","shape_pt_lon":"-86.747765","shape_pt_sequence":"178","shape_dist_traveled":"6.4125"},{"shape_id":"12292","shape_pt_lat":"36.115489","shape_pt_lon":"-86.747543","shape_pt_sequence":"179","shape_dist_traveled":"6.4673"},{"shape_id":"12292","shape_pt_lat":"36.115124","shape_pt_lon":"-86.747366","shape_pt_sequence":"180","shape_dist_traveled":"6.5113"},{"shape_id":"12292","shape_pt_lat":"36.114633","shape_pt_lon":"-86.74713","shape_pt_sequence":"181","shape_dist_traveled":"6.5701"},{"shape_id":"12292","shape_pt_lat":"36.114607","shape_pt_lon":"-86.747117","shape_pt_sequence":"182","shape_dist_traveled":"6.5733"},{"shape_id":"12292","shape_pt_lat":"36.114301","shape_pt_lon":"-86.746958","shape_pt_sequence":"183","shape_dist_traveled":"6.6101"},{"shape_id":"12292","shape_pt_lat":"36.113895","shape_pt_lon":"-86.746754","shape_pt_sequence":"184","shape_dist_traveled":"6.6585"},{"shape_id":"12292","shape_pt_lat":"36.113723","shape_pt_lon":"-86.746651","shape_pt_sequence":"185","shape_dist_traveled":"6.6809"},{"shape_id":"12292","shape_pt_lat":"36.113102","shape_pt_lon":"-86.746331","shape_pt_sequence":"186","shape_dist_traveled":"6.7554"},{"shape_id":"12292","shape_pt_lat":"36.112781","shape_pt_lon":"-86.74617","shape_pt_sequence":"187","shape_dist_traveled":"6.7944"},{"shape_id":"12292","shape_pt_lat":"36.112732","shape_pt_lon":"-86.746145","shape_pt_sequence":"188","shape_dist_traveled":"6.8007"},{"shape_id":"12292","shape_pt_lat":"36.112161","shape_pt_lon":"-86.745843","shape_pt_sequence":"189","shape_dist_traveled":"6.8702"},{"shape_id":"12292","shape_pt_lat":"36.111816","shape_pt_lon":"-86.74566","shape_pt_sequence":"190","shape_dist_traveled":"6.9114"},{"shape_id":"12292","shape_pt_lat":"36.111189","shape_pt_lon":"-86.745336","shape_pt_sequence":"191","shape_dist_traveled":"6.9872"},{"shape_id":"12292","shape_pt_lat":"36.110961","shape_pt_lon":"-86.74522","shape_pt_sequence":"192","shape_dist_traveled":"7.015"},{"shape_id":"12292","shape_pt_lat":"36.110918","shape_pt_lon":"-86.745198","shape_pt_sequence":"193","shape_dist_traveled":"7.0204"},{"shape_id":"12292","shape_pt_lat":"36.11089","shape_pt_lon":"-86.745184","shape_pt_sequence":"194","shape_dist_traveled":"7.024"},{"shape_id":"12292","shape_pt_lat":"36.110294","shape_pt_lon":"-86.744868","shape_pt_sequence":"195","shape_dist_traveled":"7.0966"},{"shape_id":"12292","shape_pt_lat":"36.110213","shape_pt_lon":"-86.744825","shape_pt_sequence":"196","shape_dist_traveled":"7.1065"},{"shape_id":"12292","shape_pt_lat":"36.110186","shape_pt_lon":"-86.744811","shape_pt_sequence":"197","shape_dist_traveled":"7.1096"},{"shape_id":"12292","shape_pt_lat":"36.109964","shape_pt_lon":"-86.744693","shape_pt_sequence":"198","shape_dist_traveled":"7.1366"},{"shape_id":"12292","shape_pt_lat":"36.109754","shape_pt_lon":"-86.744586","shape_pt_sequence":"199","shape_dist_traveled":"7.1616"},{"shape_id":"12292","shape_pt_lat":"36.109014","shape_pt_lon":"-86.744211","shape_pt_sequence":"200","shape_dist_traveled":"7.2513"},{"shape_id":"12292","shape_pt_lat":"36.108766","shape_pt_lon":"-86.744084","shape_pt_sequence":"201","shape_dist_traveled":"7.2814"},{"shape_id":"12292","shape_pt_lat":"36.108627","shape_pt_lon":"-86.744012","shape_pt_sequence":"202","shape_dist_traveled":"7.2976"},{"shape_id":"12292","shape_pt_lat":"36.108062","shape_pt_lon":"-86.743725","shape_pt_sequence":"203","shape_dist_traveled":"7.3657"},{"shape_id":"12292","shape_pt_lat":"36.107598","shape_pt_lon":"-86.743492","shape_pt_sequence":"204","shape_dist_traveled":"7.4218"},{"shape_id":"12292","shape_pt_lat":"36.107101","shape_pt_lon":"-86.743244","shape_pt_sequence":"205","shape_dist_traveled":"7.482"},{"shape_id":"12292","shape_pt_lat":"36.106382","shape_pt_lon":"-86.742879","shape_pt_sequence":"206","shape_dist_traveled":"7.5694"},{"shape_id":"12292","shape_pt_lat":"36.106126","shape_pt_lon":"-86.74275","shape_pt_sequence":"207","shape_dist_traveled":"7.5995"},{"shape_id":"12292","shape_pt_lat":"36.10521","shape_pt_lon":"-86.742289","shape_pt_sequence":"208","shape_dist_traveled":"7.7104"},{"shape_id":"12292","shape_pt_lat":"36.105152","shape_pt_lon":"-86.742259","shape_pt_sequence":"209","shape_dist_traveled":"7.7171"},{"shape_id":"12292","shape_pt_lat":"36.104471","shape_pt_lon":"-86.741919","shape_pt_sequence":"210","shape_dist_traveled":"7.7997"},{"shape_id":"12292","shape_pt_lat":"36.104328","shape_pt_lon":"-86.741848","shape_pt_sequence":"211","shape_dist_traveled":"7.8172"},{"shape_id":"12292","shape_pt_lat":"36.104174","shape_pt_lon":"-86.741769","shape_pt_sequence":"212","shape_dist_traveled":"7.8356"},{"shape_id":"12292","shape_pt_lat":"36.104055","shape_pt_lon":"-86.741709","shape_pt_sequence":"213","shape_dist_traveled":"7.8495"},{"shape_id":"12292","shape_pt_lat":"36.10319","shape_pt_lon":"-86.741273","shape_pt_sequence":"214","shape_dist_traveled":"7.954"},{"shape_id":"12292","shape_pt_lat":"36.102951","shape_pt_lon":"-86.741152","shape_pt_sequence":"215","shape_dist_traveled":"7.9832"},{"shape_id":"12292","shape_pt_lat":"36.102611","shape_pt_lon":"-86.74098","shape_pt_sequence":"216","shape_dist_traveled":"8.0241"},{"shape_id":"12292","shape_pt_lat":"36.102216","shape_pt_lon":"-86.740781","shape_pt_sequence":"217","shape_dist_traveled":"8.0716"},{"shape_id":"12292","shape_pt_lat":"36.102164","shape_pt_lon":"-86.740754","shape_pt_sequence":"218","shape_dist_traveled":"8.0779"},{"shape_id":"12292","shape_pt_lat":"36.101783","shape_pt_lon":"-86.740557","shape_pt_sequence":"219","shape_dist_traveled":"8.1245"},{"shape_id":"12292","shape_pt_lat":"36.101522","shape_pt_lon":"-86.740422","shape_pt_sequence":"220","shape_dist_traveled":"8.1559"},{"shape_id":"12292","shape_pt_lat":"36.10128","shape_pt_lon":"-86.740296","shape_pt_sequence":"221","shape_dist_traveled":"8.1851"},{"shape_id":"12292","shape_pt_lat":"36.101132","shape_pt_lon":"-86.74022","shape_pt_sequence":"222","shape_dist_traveled":"8.2025"},{"shape_id":"12292","shape_pt_lat":"36.100854","shape_pt_lon":"-86.74008","shape_pt_sequence":"223","shape_dist_traveled":"8.2371"},{"shape_id":"12292","shape_pt_lat":"36.100566","shape_pt_lon":"-86.739932","shape_pt_sequence":"224","shape_dist_traveled":"8.2716"},{"shape_id":"12292","shape_pt_lat":"36.100326","shape_pt_lon":"-86.739811","shape_pt_sequence":"225","shape_dist_traveled":"8.3008"},{"shape_id":"12292","shape_pt_lat":"36.099874","shape_pt_lon":"-86.739578","shape_pt_sequence":"226","shape_dist_traveled":"8.3546"},{"shape_id":"12292","shape_pt_lat":"36.099623","shape_pt_lon":"-86.73945","shape_pt_sequence":"227","shape_dist_traveled":"8.3851"},{"shape_id":"12292","shape_pt_lat":"36.09937","shape_pt_lon":"-86.73932","shape_pt_sequence":"228","shape_dist_traveled":"8.4161"},{"shape_id":"12292","shape_pt_lat":"36.098821","shape_pt_lon":"-86.739041","shape_pt_sequence":"229","shape_dist_traveled":"8.482"},{"shape_id":"12292","shape_pt_lat":"36.098523","shape_pt_lon":"-86.738888","shape_pt_sequence":"230","shape_dist_traveled":"8.5188"},{"shape_id":"12292","shape_pt_lat":"36.098409","shape_pt_lon":"-86.738829","shape_pt_sequence":"231","shape_dist_traveled":"8.5318"},{"shape_id":"12292","shape_pt_lat":"36.097778","shape_pt_lon":"-86.738501","shape_pt_sequence":"232","shape_dist_traveled":"8.6089"},{"shape_id":"12292","shape_pt_lat":"36.097467","shape_pt_lon":"-86.738339","shape_pt_sequence":"233","shape_dist_traveled":"8.6466"},{"shape_id":"12292","shape_pt_lat":"36.097085","shape_pt_lon":"-86.738138","shape_pt_sequence":"234","shape_dist_traveled":"8.6932"},{"shape_id":"12292","shape_pt_lat":"36.096523","shape_pt_lon":"-86.737843","shape_pt_sequence":"235","shape_dist_traveled":"8.7604"},{"shape_id":"12292","shape_pt_lat":"36.096149","shape_pt_lon":"-86.737654","shape_pt_sequence":"236","shape_dist_traveled":"8.8057"},{"shape_id":"12292","shape_pt_lat":"36.095741","shape_pt_lon":"-86.737448","shape_pt_sequence":"237","shape_dist_traveled":"8.8555"},{"shape_id":"12292","shape_pt_lat":"36.09557","shape_pt_lon":"-86.737359","shape_pt_sequence":"238","shape_dist_traveled":"8.8761"},{"shape_id":"12292","shape_pt_lat":"36.095096","shape_pt_lon":"-86.737133","shape_pt_sequence":"239","shape_dist_traveled":"8.9328"},{"shape_id":"12292","shape_pt_lat":"36.094869","shape_pt_lon":"-86.73702","shape_pt_sequence":"240","shape_dist_traveled":"8.9606"},{"shape_id":"12292","shape_pt_lat":"36.094571","shape_pt_lon":"-86.736863","shape_pt_sequence":"241","shape_dist_traveled":"8.9965"},{"shape_id":"12292","shape_pt_lat":"36.09417","shape_pt_lon":"-86.73666","shape_pt_sequence":"242","shape_dist_traveled":"9.0449"},{"shape_id":"12292","shape_pt_lat":"36.093702","shape_pt_lon":"-86.736431","shape_pt_sequence":"243","shape_dist_traveled":"9.1006"},{"shape_id":"12292","shape_pt_lat":"36.093365","shape_pt_lon":"-86.736256","shape_pt_sequence":"244","shape_dist_traveled":"9.1419"},{"shape_id":"12292","shape_pt_lat":"36.092772","shape_pt_lon":"-86.73595","shape_pt_sequence":"245","shape_dist_traveled":"9.2132"},{"shape_id":"12292","shape_pt_lat":"36.092451","shape_pt_lon":"-86.735778","shape_pt_sequence":"246","shape_dist_traveled":"9.2526"},{"shape_id":"12292","shape_pt_lat":"36.092404","shape_pt_lon":"-86.735751","shape_pt_sequence":"247","shape_dist_traveled":"9.2589"},{"shape_id":"12292","shape_pt_lat":"36.092215","shape_pt_lon":"-86.735639","shape_pt_sequence":"248","shape_dist_traveled":"9.2822"},{"shape_id":"12292","shape_pt_lat":"36.092015","shape_pt_lon":"-86.735514","shape_pt_sequence":"249","shape_dist_traveled":"9.3068"},{"shape_id":"12292","shape_pt_lat":"36.091844","shape_pt_lon":"-86.735387","shape_pt_sequence":"250","shape_dist_traveled":"9.3292"},{"shape_id":"12292","shape_pt_lat":"36.091547","shape_pt_lon":"-86.735156","shape_pt_sequence":"251","shape_dist_traveled":"9.3687"},{"shape_id":"12292","shape_pt_lat":"36.091405","shape_pt_lon":"-86.735039","shape_pt_sequence":"252","shape_dist_traveled":"9.3881"},{"shape_id":"12292","shape_pt_lat":"36.091317","shape_pt_lon":"-86.734967","shape_pt_sequence":"253","shape_dist_traveled":"9.3989"},{"shape_id":"12292","shape_pt_lat":"36.091177","shape_pt_lon":"-86.734833","shape_pt_sequence":"254","shape_dist_traveled":"9.4189"},{"shape_id":"12292","shape_pt_lat":"36.090896","shape_pt_lon":"-86.734541","shape_pt_sequence":"255","shape_dist_traveled":"9.4594"},{"shape_id":"12292","shape_pt_lat":"36.090857","shape_pt_lon":"-86.7345","shape_pt_sequence":"256","shape_dist_traveled":"9.4658"},{"shape_id":"12292","shape_pt_lat":"36.090619","shape_pt_lon":"-86.734262","shape_pt_sequence":"257","shape_dist_traveled":"9.5"},{"shape_id":"12292","shape_pt_lat":"36.090281","shape_pt_lon":"-86.733879","shape_pt_sequence":"258","shape_dist_traveled":"9.5502"},{"shape_id":"12292","shape_pt_lat":"36.090104","shape_pt_lon":"-86.733687","shape_pt_sequence":"259","shape_dist_traveled":"9.5771"},{"shape_id":"12292","shape_pt_lat":"36.089937","shape_pt_lon":"-86.733506","shape_pt_sequence":"260","shape_dist_traveled":"9.602"},{"shape_id":"12292","shape_pt_lat":"36.089245","shape_pt_lon":"-86.732768","shape_pt_sequence":"261","shape_dist_traveled":"9.7034"},{"shape_id":"12292","shape_pt_lat":"36.089197","shape_pt_lon":"-86.732717","shape_pt_sequence":"262","shape_dist_traveled":"9.7106"},{"shape_id":"12292","shape_pt_lat":"36.088967","shape_pt_lon":"-86.732462","shape_pt_sequence":"263","shape_dist_traveled":"9.7446"},{"shape_id":"12292","shape_pt_lat":"36.08827","shape_pt_lon":"-86.7317","shape_pt_sequence":"264","shape_dist_traveled":"9.8481"},{"shape_id":"12292","shape_pt_lat":"36.088007","shape_pt_lon":"-86.731413","shape_pt_sequence":"265","shape_dist_traveled":"9.8878"},{"shape_id":"12292","shape_pt_lat":"36.087549","shape_pt_lon":"-86.730923","shape_pt_sequence":"266","shape_dist_traveled":"9.9545"},{"shape_id":"12292","shape_pt_lat":"36.087282","shape_pt_lon":"-86.730638","shape_pt_sequence":"267","shape_dist_traveled":"9.9942"},{"shape_id":"12292","shape_pt_lat":"36.087029","shape_pt_lon":"-86.730353","shape_pt_sequence":"268","shape_dist_traveled":"10.0317"},{"shape_id":"12292","shape_pt_lat":"36.086912","shape_pt_lon":"-86.73023","shape_pt_sequence":"269","shape_dist_traveled":"10.0487"},{"shape_id":"12292","shape_pt_lat":"36.086759","shape_pt_lon":"-86.730068","shape_pt_sequence":"270","shape_dist_traveled":"10.0722"},{"shape_id":"12292","shape_pt_lat":"36.086558","shape_pt_lon":"-86.729844","shape_pt_sequence":"271","shape_dist_traveled":"10.1019"},{"shape_id":"12292","shape_pt_lat":"36.086327","shape_pt_lon":"-86.729594","shape_pt_sequence":"272","shape_dist_traveled":"10.1359"},{"shape_id":"12292","shape_pt_lat":"36.086104","shape_pt_lon":"-86.729361","shape_pt_sequence":"273","shape_dist_traveled":"10.1686"},{"shape_id":"12292","shape_pt_lat":"36.086067","shape_pt_lon":"-86.729321","shape_pt_sequence":"274","shape_dist_traveled":"10.1736"},{"shape_id":"12292","shape_pt_lat":"36.085951","shape_pt_lon":"-86.729201","shape_pt_sequence":"275","shape_dist_traveled":"10.1906"},{"shape_id":"12292","shape_pt_lat":"36.08568","shape_pt_lon":"-86.728919","shape_pt_sequence":"276","shape_dist_traveled":"10.2297"},{"shape_id":"12292","shape_pt_lat":"36.085524","shape_pt_lon":"-86.728753","shape_pt_sequence":"277","shape_dist_traveled":"10.2531"},{"shape_id":"12292","shape_pt_lat":"36.085346","shape_pt_lon":"-86.728578","shape_pt_sequence":"278","shape_dist_traveled":"10.2787"},{"shape_id":"12292","shape_pt_lat":"36.085137","shape_pt_lon":"-86.728395","shape_pt_sequence":"279","shape_dist_traveled":"10.3067"},{"shape_id":"12292","shape_pt_lat":"36.084951","shape_pt_lon":"-86.72824","shape_pt_sequence":"280","shape_dist_traveled":"10.332"},{"shape_id":"12292","shape_pt_lat":"36.084803","shape_pt_lon":"-86.72813","shape_pt_sequence":"281","shape_dist_traveled":"10.3517"},{"shape_id":"12292","shape_pt_lat":"36.084498","shape_pt_lon":"-86.727948","shape_pt_sequence":"282","shape_dist_traveled":"10.3893"},{"shape_id":"12292","shape_pt_lat":"36.084293","shape_pt_lon":"-86.727845","shape_pt_sequence":"283","shape_dist_traveled":"10.414"},{"shape_id":"12292","shape_pt_lat":"36.084236","shape_pt_lon":"-86.727817","shape_pt_sequence":"284","shape_dist_traveled":"10.4207"},{"shape_id":"12292","shape_pt_lat":"36.083928","shape_pt_lon":"-86.727665","shape_pt_sequence":"285","shape_dist_traveled":"10.4571"},{"shape_id":"12292","shape_pt_lat":"36.083662","shape_pt_lon":"-86.727565","shape_pt_sequence":"286","shape_dist_traveled":"10.4884"},{"shape_id":"12292","shape_pt_lat":"36.083456","shape_pt_lon":"-86.727489","shape_pt_sequence":"287","shape_dist_traveled":"10.5124"},{"shape_id":"12292","shape_pt_lat":"36.083381","shape_pt_lon":"-86.727467","shape_pt_sequence":"288","shape_dist_traveled":"10.5217"},{"shape_id":"12292","shape_pt_lat":"36.083279","shape_pt_lon":"-86.727436","shape_pt_sequence":"289","shape_dist_traveled":"10.5331"},{"shape_id":"12292","shape_pt_lat":"36.082671","shape_pt_lon":"-86.727249","shape_pt_sequence":"290","shape_dist_traveled":"10.6032"},{"shape_id":"12292","shape_pt_lat":"36.082584","shape_pt_lon":"-86.727222","shape_pt_sequence":"291","shape_dist_traveled":"10.6134"},{"shape_id":"12292","shape_pt_lat":"36.082323","shape_pt_lon":"-86.727142","shape_pt_sequence":"292","shape_dist_traveled":"10.6432"},{"shape_id":"12292","shape_pt_lat":"36.081542","shape_pt_lon":"-86.72691","shape_pt_sequence":"293","shape_dist_traveled":"10.7337"},{"shape_id":"12292","shape_pt_lat":"36.08138","shape_pt_lon":"-86.726863","shape_pt_sequence":"294","shape_dist_traveled":"10.7521"},{"shape_id":"12292","shape_pt_lat":"36.080505","shape_pt_lon":"-86.726616","shape_pt_sequence":"295","shape_dist_traveled":"10.8525"},{"shape_id":"12292","shape_pt_lat":"36.080447","shape_pt_lon":"-86.7266","shape_pt_sequence":"296","shape_dist_traveled":"10.8589"},{"shape_id":"12292","shape_pt_lat":"36.079611","shape_pt_lon":"-86.726342","shape_pt_sequence":"297","shape_dist_traveled":"10.9556"},{"shape_id":"12292","shape_pt_lat":"36.07958","shape_pt_lon":"-86.726333","shape_pt_sequence":"298","shape_dist_traveled":"10.9586"},{"shape_id":"12292","shape_pt_lat":"36.079476","shape_pt_lon":"-86.726301","shape_pt_sequence":"299","shape_dist_traveled":"10.971"},{"shape_id":"12292","shape_pt_lat":"36.078813","shape_pt_lon":"-86.726112","shape_pt_sequence":"300","shape_dist_traveled":"11.0469"},{"shape_id":"12292","shape_pt_lat":"36.07871","shape_pt_lon":"-86.726079","shape_pt_sequence":"301","shape_dist_traveled":"11.0593"},{"shape_id":"12292","shape_pt_lat":"36.078606","shape_pt_lon":"-86.726045","shape_pt_sequence":"302","shape_dist_traveled":"11.0707"},{"shape_id":"12292","shape_pt_lat":"36.077895","shape_pt_lon":"-86.725814","shape_pt_sequence":"303","shape_dist_traveled":"11.1534"},{"shape_id":"12292","shape_pt_lat":"36.077587","shape_pt_lon":"-86.725712","shape_pt_sequence":"304","shape_dist_traveled":"11.1886"},{"shape_id":"12292","shape_pt_lat":"36.077184","shape_pt_lon":"-86.725584","shape_pt_sequence":"305","shape_dist_traveled":"11.2359"},{"shape_id":"12292","shape_pt_lat":"36.077091","shape_pt_lon":"-86.725553","shape_pt_sequence":"306","shape_dist_traveled":"11.2463"},{"shape_id":"12292","shape_pt_lat":"36.076813","shape_pt_lon":"-86.725464","shape_pt_sequence":"307","shape_dist_traveled":"11.2783"},{"shape_id":"12292","shape_pt_lat":"36.076631","shape_pt_lon":"-86.725406","shape_pt_sequence":"308","shape_dist_traveled":"11.2999"},{"shape_id":"12292","shape_pt_lat":"36.076236","shape_pt_lon":"-86.725284","shape_pt_sequence":"309","shape_dist_traveled":"11.3453"},{"shape_id":"12292","shape_pt_lat":"36.075948","shape_pt_lon":"-86.725195","shape_pt_sequence":"310","shape_dist_traveled":"11.3783"},{"shape_id":"12292","shape_pt_lat":"36.075821","shape_pt_lon":"-86.725157","shape_pt_sequence":"311","shape_dist_traveled":"11.3928"},{"shape_id":"12292","shape_pt_lat":"36.075531","shape_pt_lon":"-86.725071","shape_pt_sequence":"312","shape_dist_traveled":"11.4266"},{"shape_id":"12292","shape_pt_lat":"36.075251","shape_pt_lon":"-86.724987","shape_pt_sequence":"313","shape_dist_traveled":"11.4586"},{"shape_id":"12292","shape_pt_lat":"36.075033","shape_pt_lon":"-86.724927","shape_pt_sequence":"314","shape_dist_traveled":"11.4831"},{"shape_id":"12292","shape_pt_lat":"36.074864","shape_pt_lon":"-86.724879","shape_pt_sequence":"315","shape_dist_traveled":"11.5027"},{"shape_id":"12292","shape_pt_lat":"36.074669","shape_pt_lon":"-86.724813","shape_pt_sequence":"316","shape_dist_traveled":"11.5253"},{"shape_id":"12292","shape_pt_lat":"36.074053","shape_pt_lon":"-86.724623","shape_pt_sequence":"317","shape_dist_traveled":"11.5964"},{"shape_id":"12292","shape_pt_lat":"36.073725","shape_pt_lon":"-86.724522","shape_pt_sequence":"318","shape_dist_traveled":"11.6347"},{"shape_id":"12292","shape_pt_lat":"36.073437","shape_pt_lon":"-86.724433","shape_pt_sequence":"319","shape_dist_traveled":"11.6674"},{"shape_id":"12292","shape_pt_lat":"36.072792","shape_pt_lon":"-86.724232","shape_pt_sequence":"320","shape_dist_traveled":"11.7417"},{"shape_id":"12292","shape_pt_lat":"36.072628","shape_pt_lon":"-86.724179","shape_pt_sequence":"321","shape_dist_traveled":"11.7613"},{"shape_id":"12292","shape_pt_lat":"36.072492","shape_pt_lon":"-86.724137","shape_pt_sequence":"322","shape_dist_traveled":"11.7768"},{"shape_id":"12292","shape_pt_lat":"36.072329","shape_pt_lon":"-86.724084","shape_pt_sequence":"323","shape_dist_traveled":"11.7955"},{"shape_id":"12292","shape_pt_lat":"36.072163","shape_pt_lon":"-86.724019","shape_pt_sequence":"324","shape_dist_traveled":"11.8154"},{"shape_id":"12292","shape_pt_lat":"36.071956","shape_pt_lon":"-86.723943","shape_pt_sequence":"325","shape_dist_traveled":"11.8392"},{"shape_id":"12292","shape_pt_lat":"36.071899","shape_pt_lon":"-86.723915","shape_pt_sequence":"326","shape_dist_traveled":"11.8459"},{"shape_id":"12292","shape_pt_lat":"36.071825","shape_pt_lon":"-86.723876","shape_pt_sequence":"327","shape_dist_traveled":"11.8554"},{"shape_id":"12292","shape_pt_lat":"36.071645","shape_pt_lon":"-86.723767","shape_pt_sequence":"328","shape_dist_traveled":"11.8778"},{"shape_id":"12292","shape_pt_lat":"36.071399","shape_pt_lon":"-86.723597","shape_pt_sequence":"329","shape_dist_traveled":"11.9087"},{"shape_id":"12292","shape_pt_lat":"36.071216","shape_pt_lon":"-86.723416","shape_pt_sequence":"330","shape_dist_traveled":"11.9351"},{"shape_id":"12292","shape_pt_lat":"36.071054","shape_pt_lon":"-86.723238","shape_pt_sequence":"331","shape_dist_traveled":"11.9591"},{"shape_id":"12292","shape_pt_lat":"36.070918","shape_pt_lon":"-86.723067","shape_pt_sequence":"332","shape_dist_traveled":"11.9811"},{"shape_id":"12292","shape_pt_lat":"36.070768","shape_pt_lon":"-86.72285","shape_pt_sequence":"333","shape_dist_traveled":"12.0066"},{"shape_id":"12292","shape_pt_lat":"36.070495","shape_pt_lon":"-86.722422","shape_pt_sequence":"334","shape_dist_traveled":"12.0556"},{"shape_id":"12292","shape_pt_lat":"36.070295","shape_pt_lon":"-86.722098","shape_pt_sequence":"335","shape_dist_traveled":"12.092"},{"shape_id":"12292","shape_pt_lat":"36.070056","shape_pt_lon":"-86.721713","shape_pt_sequence":"336","shape_dist_traveled":"12.1362"},{"shape_id":"12292","shape_pt_lat":"36.06968","shape_pt_lon":"-86.721109","shape_pt_sequence":"337","shape_dist_traveled":"12.2038"},{"shape_id":"12292","shape_pt_lat":"36.069191","shape_pt_lon":"-86.720326","shape_pt_sequence":"338","shape_dist_traveled":"12.2922"},{"shape_id":"12292","shape_pt_lat":"36.069137","shape_pt_lon":"-86.720245","shape_pt_sequence":"339","shape_dist_traveled":"12.3022"},{"shape_id":"12292","shape_pt_lat":"36.068942","shape_pt_lon":"-86.719984","shape_pt_sequence":"340","shape_dist_traveled":"12.3341"},{"shape_id":"12292","shape_pt_lat":"36.068866","shape_pt_lon":"-86.71989","shape_pt_sequence":"341","shape_dist_traveled":"12.3461"},{"shape_id":"12292","shape_pt_lat":"36.068698","shape_pt_lon":"-86.71969","shape_pt_sequence":"342","shape_dist_traveled":"12.3723"},{"shape_id":"12292","shape_pt_lat":"36.068529","shape_pt_lon":"-86.71948","shape_pt_sequence":"343","shape_dist_traveled":"12.3985"},{"shape_id":"12292","shape_pt_lat":"36.068356","shape_pt_lon":"-86.719287","shape_pt_sequence":"344","shape_dist_traveled":"12.4247"},{"shape_id":"12292","shape_pt_lat":"36.068257","shape_pt_lon":"-86.719177","shape_pt_sequence":"345","shape_dist_traveled":"12.4396"},{"shape_id":"12292","shape_pt_lat":"36.068189","shape_pt_lon":"-86.719106","shape_pt_sequence":"346","shape_dist_traveled":"12.4496"},{"shape_id":"12292","shape_pt_lat":"36.068059","shape_pt_lon":"-86.718978","shape_pt_sequence":"347","shape_dist_traveled":"12.468"},{"shape_id":"12292","shape_pt_lat":"36.0678","shape_pt_lon":"-86.718746","shape_pt_sequence":"348","shape_dist_traveled":"12.5038"},{"shape_id":"12292","shape_pt_lat":"36.067583","shape_pt_lon":"-86.718567","shape_pt_sequence":"349","shape_dist_traveled":"12.5321"},{"shape_id":"12292","shape_pt_lat":"36.067381","shape_pt_lon":"-86.718408","shape_pt_sequence":"350","shape_dist_traveled":"12.5596"},{"shape_id":"12292","shape_pt_lat":"36.067259","shape_pt_lon":"-86.718315","shape_pt_sequence":"351","shape_dist_traveled":"12.5757"},{"shape_id":"12292","shape_pt_lat":"36.066965","shape_pt_lon":"-86.718125","shape_pt_sequence":"352","shape_dist_traveled":"12.6128"},{"shape_id":"12292","shape_pt_lat":"36.066746","shape_pt_lon":"-86.717991","shape_pt_sequence":"353","shape_dist_traveled":"12.6397"},{"shape_id":"12292","shape_pt_lat":"36.066682","shape_pt_lon":"-86.717955","shape_pt_sequence":"354","shape_dist_traveled":"12.6473"},{"shape_id":"12292","shape_pt_lat":"36.066419","shape_pt_lon":"-86.717811","shape_pt_sequence":"355","shape_dist_traveled":"12.68"},{"shape_id":"12292","shape_pt_lat":"36.06627","shape_pt_lon":"-86.717733","shape_pt_sequence":"356","shape_dist_traveled":"12.6974"},{"shape_id":"12292","shape_pt_lat":"36.065827","shape_pt_lon":"-86.717534","shape_pt_sequence":"357","shape_dist_traveled":"12.7506"},{"shape_id":"12292","shape_pt_lat":"36.065553","shape_pt_lon":"-86.717437","shape_pt_sequence":"358","shape_dist_traveled":"12.7829"},{"shape_id":"12292","shape_pt_lat":"36.065351","shape_pt_lon":"-86.717375","shape_pt_sequence":"359","shape_dist_traveled":"12.8054"},{"shape_id":"12292","shape_pt_lat":"36.065057","shape_pt_lon":"-86.717302","shape_pt_sequence":"360","shape_dist_traveled":"12.8391"},{"shape_id":"12292","shape_pt_lat":"36.064969","shape_pt_lon":"-86.71728","shape_pt_sequence":"361","shape_dist_traveled":"12.8493"},{"shape_id":"12292","shape_pt_lat":"36.064713","shape_pt_lon":"-86.717222","shape_pt_sequence":"362","shape_dist_traveled":"12.8788"},{"shape_id":"12292","shape_pt_lat":"36.064205","shape_pt_lon":"-86.717135","shape_pt_sequence":"363","shape_dist_traveled":"12.9363"},{"shape_id":"12292","shape_pt_lat":"36.063764","shape_pt_lon":"-86.717071","shape_pt_sequence":"364","shape_dist_traveled":"12.9856"},{"shape_id":"12292","shape_pt_lat":"36.063636","shape_pt_lon":"-86.717122","shape_pt_sequence":"365","shape_dist_traveled":"13.0001"},{"shape_id":"12292","shape_pt_lat":"36.063439","shape_pt_lon":"-86.71709","shape_pt_sequence":"366","shape_dist_traveled":"13.0224"},{"shape_id":"12292","shape_pt_lat":"36.063372","shape_pt_lon":"-86.717081","shape_pt_sequence":"367","shape_dist_traveled":"13.0304"},{"shape_id":"12292","shape_pt_lat":"36.06299","shape_pt_lon":"-86.717022","shape_pt_sequence":"368","shape_dist_traveled":"13.0738"},{"shape_id":"12292","shape_pt_lat":"36.062856","shape_pt_lon":"-86.717","shape_pt_sequence":"369","shape_dist_traveled":"13.0889"},{"shape_id":"12292","shape_pt_lat":"36.062499","shape_pt_lon":"-86.716946","shape_pt_sequence":"370","shape_dist_traveled":"13.1292"},{"shape_id":"12292","shape_pt_lat":"36.062326","shape_pt_lon":"-86.716911","shape_pt_sequence":"371","shape_dist_traveled":"13.1484"},{"shape_id":"12292","shape_pt_lat":"36.062264","shape_pt_lon":"-86.716899","shape_pt_sequence":"372","shape_dist_traveled":"13.1555"},{"shape_id":"12292","shape_pt_lat":"36.061769","shape_pt_lon":"-86.716815","shape_pt_sequence":"373","shape_dist_traveled":"13.211"},{"shape_id":"12292","shape_pt_lat":"36.06162","shape_pt_lon":"-86.716788","shape_pt_sequence":"374","shape_dist_traveled":"13.2282"},{"shape_id":"12292","shape_pt_lat":"36.061291","shape_pt_lon":"-86.716733","shape_pt_sequence":"375","shape_dist_traveled":"13.2656"},{"shape_id":"12292","shape_pt_lat":"36.060893","shape_pt_lon":"-86.716662","shape_pt_sequence":"376","shape_dist_traveled":"13.31"},{"shape_id":"12292","shape_pt_lat":"36.060865","shape_pt_lon":"-86.716657","shape_pt_sequence":"377","shape_dist_traveled":"13.3141"},{"shape_id":"12292","shape_pt_lat":"36.060071","shape_pt_lon":"-86.716501","shape_pt_sequence":"378","shape_dist_traveled":"13.4032"},{"shape_id":"12292","shape_pt_lat":"36.059867","shape_pt_lon":"-86.716461","shape_pt_sequence":"379","shape_dist_traveled":"13.4264"},{"shape_id":"12292","shape_pt_lat":"36.059373","shape_pt_lon":"-86.716389","shape_pt_sequence":"380","shape_dist_traveled":"13.4828"},{"shape_id":"12292","shape_pt_lat":"36.059032","shape_pt_lon":"-86.716341","shape_pt_sequence":"381","shape_dist_traveled":"13.521"},{"shape_id":"12292","shape_pt_lat":"36.058922","shape_pt_lon":"-86.716325","shape_pt_sequence":"382","shape_dist_traveled":"13.5331"},{"shape_id":"12292","shape_pt_lat":"36.058645","shape_pt_lon":"-86.716272","shape_pt_sequence":"383","shape_dist_traveled":"13.5645"},{"shape_id":"12292","shape_pt_lat":"36.058512","shape_pt_lon":"-86.716248","shape_pt_sequence":"384","shape_dist_traveled":"13.5796"},{"shape_id":"12292","shape_pt_lat":"36.058374","shape_pt_lon":"-86.716221","shape_pt_sequence":"385","shape_dist_traveled":"13.5959"},{"shape_id":"12292","shape_pt_lat":"36.058085","shape_pt_lon":"-86.716171","shape_pt_sequence":"386","shape_dist_traveled":"13.6281"},{"shape_id":"12292","shape_pt_lat":"36.057925","shape_pt_lon":"-86.716142","shape_pt_sequence":"387","shape_dist_traveled":"13.6464"},{"shape_id":"12292","shape_pt_lat":"36.05696","shape_pt_lon":"-86.71596","shape_pt_sequence":"388","shape_dist_traveled":"13.7556"},{"shape_id":"12292","shape_pt_lat":"36.056601","shape_pt_lon":"-86.715883","shape_pt_sequence":"389","shape_dist_traveled":"13.7962"},{"shape_id":"12292","shape_pt_lat":"36.056319","shape_pt_lon":"-86.715821","shape_pt_sequence":"390","shape_dist_traveled":"13.8287"},{"shape_id":"12292","shape_pt_lat":"36.056077","shape_pt_lon":"-86.715771","shape_pt_sequence":"391","shape_dist_traveled":"13.856"},{"shape_id":"12292","shape_pt_lat":"36.055933","shape_pt_lon":"-86.715736","shape_pt_sequence":"392","shape_dist_traveled":"13.8723"},{"shape_id":"12292","shape_pt_lat":"36.055032","shape_pt_lon":"-86.715512","shape_pt_sequence":"393","shape_dist_traveled":"13.9753"},{"shape_id":"12292","shape_pt_lat":"36.054107","shape_pt_lon":"-86.715219","shape_pt_sequence":"394","shape_dist_traveled":"14.0815"},{"shape_id":"12292","shape_pt_lat":"36.05364","shape_pt_lon":"-86.715082","shape_pt_sequence":"395","shape_dist_traveled":"14.1361"},{"shape_id":"12292","shape_pt_lat":"36.053157","shape_pt_lon":"-86.714939","shape_pt_sequence":"396","shape_dist_traveled":"14.1916"},{"shape_id":"12292","shape_pt_lat":"36.052413","shape_pt_lon":"-86.714718","shape_pt_sequence":"397","shape_dist_traveled":"14.2768"},{"shape_id":"12292","shape_pt_lat":"36.052211","shape_pt_lon":"-86.714658","shape_pt_sequence":"398","shape_dist_traveled":"14.3005"},{"shape_id":"12292","shape_pt_lat":"36.0519","shape_pt_lon":"-86.714555","shape_pt_sequence":"399","shape_dist_traveled":"14.3357"},{"shape_id":"12292","shape_pt_lat":"36.051517","shape_pt_lon":"-86.714427","shape_pt_sequence":"400","shape_dist_traveled":"14.3801"},{"shape_id":"12292","shape_pt_lat":"36.051246","shape_pt_lon":"-86.714339","shape_pt_sequence":"401","shape_dist_traveled":"14.4121"},{"shape_id":"12292","shape_pt_lat":"36.050519","shape_pt_lon":"-86.714133","shape_pt_sequence":"402","shape_dist_traveled":"14.4953"},{"shape_id":"12292","shape_pt_lat":"36.050295","shape_pt_lon":"-86.71407","shape_pt_sequence":"403","shape_dist_traveled":"14.5208"},{"shape_id":"12292","shape_pt_lat":"36.049507","shape_pt_lon":"-86.713866","shape_pt_sequence":"404","shape_dist_traveled":"14.6108"}]